pygpg/__init__.py
pygpg/exceptions.py
pygpg/gpg_key.py
pygpg/key_owner.py
pygpg/main.py
pygpg/commands/__init__.py
pygpg/commands/import_export.py
pygpg/commands/ls.py
pygpg/commands/renew.py
pygpg/display/__init__.py
pygpg/display/display_key.py
pygpg/display/display_key_owner.py
pygpg/display/trust_value_colors.py
pygpg/enums/__init__.py
pygpg/enums/key_algorithm.py
pygpg/enums/key_capability.py
pygpg/enums/key_token.py
pygpg/enums/key_type.py
pygpg/enums/trust_value.py
pygpg/gnupg_extension/__init__.py
pygpg/gnupg_extension/edit_key.py
pygpg/gnupg_extension/export_key.py
pygpg/utils/__init__.py
pygpg/utils/keys.py
pygpg-0.4.1.dist-info/LICENSE
pygpg-0.4.1.dist-info/METADATA
pygpg-0.4.1.dist-info/WHEEL
pygpg-0.4.1.dist-info/entry_points.txt
pygpg-0.4.1.dist-info/top_level.txt
pygpg-0.4.1.dist-info/RECORD
