Metadata-Version: 2.1
Name: pygpg
Version: 0.4.1
Summary: A thin wrapper around GPG with friendlier command line options!
Home-page: https://github.com/marier-nico/pg
Author: Nicolas Marier
Author-email: software@nmarier.com
License: UNKNOWN
Keywords: gpg,cli
Platform: UNKNOWN
Requires-Dist: click (~=7.1.2)
Requires-Dist: python-gnupg (~=0.4.6)
Requires-Dist: colorama (~=0.4.4) ; platform_system == "Windows"
Requires-Dist: dataclasses (~=0.8) ; python_version == "3.6"
